apilizer/.coverage
apilizer/__init__.py
apilizer/cli.py
apilizer/htmlcov/.gitignore
apilizer/htmlcov/__init___py.html
apilizer/htmlcov/cli_py.html
apilizer/htmlcov/coverage_html.js
apilizer/htmlcov/favicon_32.png
apilizer/htmlcov/index.html
apilizer/htmlcov/keybd_closed.png
apilizer/htmlcov/keybd_open.png
apilizer/htmlcov/status.json
apilizer/htmlcov/style.css
apilizer/htmlcov/verify_py.html
apilizer/verify.py
apilizer-0.1.3.dist-info/LICENSE
apilizer-0.1.3.dist-info/METADATA
apilizer-0.1.3.dist-info/WHEEL
apilizer-0.1.3.dist-info/entry_points.txt
apilizer-0.1.3.dist-info/RECORD
