Metadata-Version: 2.1
Name: apilizer
Version: 0.1.3
Summary: APIlizer is a python library that aims to analyze the level of maturity of REST APIs, following the Richardson maturity model
License: MIT
Author: Marco Antônio
Author-email: marcomartins06@rede.ulbra.br
Requires-Python: >=3.9,<4.0
Classifier: Development Status :: 2 - Pre-Alpha
Classifier: Environment :: Console
Classifier: Intended Audience :: Developers
Classifier: License :: OSI Approved :: MIT License
Classifier: Programming Language :: Python :: 3
Classifier: Programming Language :: Python :: 3.9
Classifier: Programming Language :: Python :: 3.10
Classifier: Programming Language :: Python :: 3.11
Classifier: Topic :: Software Development :: Libraries :: Python Modules
Requires-Dist: httpx (>=0.25.0,<0.26.0)
Requires-Dist: rich (>=13.5.2,<14.0.0)
Requires-Dist: typer (>=0.9.0,<0.10.0)
Project-URL: Bug Tracker, https://github.com/Tchez/apilizer/issues
Project-URL: Documentation, https://apilizer.readthedocs.io/en/latest/
Project-URL: Source Code, https://github.com/Tchez/apilizer
